LICENSE.txt
MANIFEST.in
README.txt
setup.py
lfc_page/__init__.py
lfc_page/forms.py
lfc_page/models.py
lfc_page/test.py
lfc_page.egg-info/PKG-INFO
lfc_page.egg-info/SOURCES.txt
lfc_page.egg-info/dependency_links.txt
lfc_page.egg-info/not-zip-safe
lfc_page.egg-info/requires.txt
lfc_page.egg-info/top_level.txt
lfc_page/locale/de/LC_MESSAGES/django.mo
lfc_page/locale/de/LC_MESSAGES/django.po